minimateria/__init__.py
minimateria/__main__.py
minimateria/auto_update.py
minimateria/craft.py
minimateria/info.py
minimateria/key_input.py
minimateria/mouse_input.py
minimateria/render.py
sprites/arrow.png
sprites/belt0.png
sprites/belt1.png
sprites/belt2.png
sprites/belt3.png
sprites/belt4.png
sprites/belt5.png
sprites/compactium crystal.png
sprites/compactium gear.png
sprites/compactium machine casing.png
sprites/compactium.png
sprites/compactor0.png
sprites/compactor1.png
sprites/compactor2.png
sprites/compactor3.png
sprites/compactor4.png
sprites/compactor5.png
sprites/crafter0.png
sprites/crafter1.png
sprites/crafter2.png
sprites/crafter3.png
sprites/crafter4.png
sprites/crafter5.png
sprites/dried compactium gear.png
sprites/dried compactium.png
sprites/pure compactium gear.png
sprites/pure compactium machine casing.png
sprites/pure compactium.png
sprites/pure compactor0.png
sprites/pure compactor1.png
sprites/pure compactor2.png
sprites/pure compactor3.png
sprites/pure compactor4.png
sprites/pure compactor5.png
sprites/smelter0.png
sprites/smelter1.png
sprites/smelter2.png
sprites/smelter3.png
sprites/smelter4.png
sprites/smelter5.png
sprites/tiny room.png
sprites/vault.png
minimateria-0.1.1.dist-info/METADATA
minimateria-0.1.1.dist-info/WHEEL
minimateria-0.1.1.dist-info/entry_points.txt
minimateria-0.1.1.dist-info/RECORD
