Metadata-Version: 2.3
Name: minimateria
Version: 0.1.1
Summary: A factory automation game set in a very limited space
Author-email: TimoAndy08 <134264827+TimoAndy08@users.noreply.github.com>
Requires-Python: >=3.13
Requires-Dist: pygame~=2.6
